pytest_gitscope/__init__.py
pytest_gitscope/diff.py
pytest_gitscope/plugin.py
pytest_gitscope/py.typed
pytest_gitscope/selector.py
pytest_gitscope-0.7.1.dist-info/METADATA
pytest_gitscope-0.7.1.dist-info/WHEEL
pytest_gitscope-0.7.1.dist-info/entry_points.txt
pytest_gitscope-0.7.1.dist-info/licenses/LICENSE
pytest_gitscope-0.7.1.dist-info/RECORD
