Metadata-Version: 2.4
Name: pytest-gitscope
Version: 0.7.1
Summary: A pragmatic pytest plugin that runs only the tests that matter, and ship faster
Project-URL: Homepage, https://github.com/johnnoone/pytest-gitscope
Project-URL: Source, https://github.com/johnnoone/pytest-gitscope
Project-URL: Tracker, https://github.com/johnnoone/pytest-gitscope/issues
Author-email: Xavier Barbosa <clint.northwood@gmail.com>
License-Expression: MIT
License-File: LICENSE
Classifier: Development Status :: 5 - Production/Stable
Classifier: Framework :: Pytest
Classifier: Intended Audience :: Developers
Classifier: Operating System :: MacOS :: MacOS X
Classifier: Operating System :: Microsoft :: Windows
Classifier: Operating System :: POSIX
Classifier: Programming Language :: Python
Classifier: Programming Language :: Python :: 3
Classifier: Programming Language :: Python :: 3 :: Only
Classifier: Programming Language :: Python :: 3.11
Classifier: Programming Language :: Python :: 3.12
Classifier: Programming Language :: Python :: 3.13
Classifier: Programming Language :: Python :: 3.14
Classifier: Topic :: Software Development :: Quality Assurance
Classifier: Topic :: Software Development :: Testing
Classifier: Topic :: Utilities
Requires-Python: >=3.11
Requires-Dist: pytest>=7.0.0
